pyperclip_pyside/__init__.py
pyperclip_pyside/__main__.py
pyperclip_pyside-1.8.2.dist-info/AUTHORS.txt
pyperclip_pyside-1.8.2.dist-info/LICENSE.txt
pyperclip_pyside-1.8.2.dist-info/METADATA
pyperclip_pyside-1.8.2.dist-info/WHEEL
pyperclip_pyside-1.8.2.dist-info/top_level.txt
pyperclip_pyside-1.8.2.dist-info/RECORD
